LICENSE
MANIFEST.in
README.md
setup.py
mylibtool/__init__.py
mylibtool/__version__.py
mylibtool.egg-info/PKG-INFO
mylibtool.egg-info/SOURCES.txt
mylibtool.egg-info/dependency_links.txt
mylibtool.egg-info/requires.txt
mylibtool.egg-info/top_level.txt
mylibtool/mydatetime/__init__.py
mylibtool/mydatetime/core.py
mylibtool/mydatetime/extract_.py
mylibtool/mydatetime/extract_prep.py
mylibtool/mydatetime/month_pair.py
mylibtool/mydatetime/timezone.py
mylibtool/wordpress/__init__.py
mylibtool/wordpress/category.py
mylibtool/wordpress/core.py
mylibtool/wordpress/custom.py
mylibtool/wordpress/files.py
mylibtool/wordpress/posts.py